{"moduleDefinition":{"range":[1,1,1,115],"value":{"type":"normal","normal":{"moduleName":{"range":[1,8,1,13],"value":["Model"]},"exposingList":{"range":[1,14,1,115],"value":{"type":"explicit","explicit":[{"range":[1,24,1,33],"value":{"type":"typeOrAlias","typeOrAlias":{"name":"Rectangle"}}},{"range":[1,34,1,37],"value":{"type":"typeOrAlias","typeOrAlias":{"name":"Rec"}}},{"range":[1,38,1,44],"value":{"type":"typeOrAlias","typeOrAlias":{"name":"Player"}}},{"range":[1,45,1,47],"value":{"type":"typeOrAlias","typeOrAlias":{"name":"Me"}}},{"range":[1,48,1,53],"value":{"type":"typeOrAlias","typeOrAlias":{"name":"Model"}}},{"range":[1,54,1,60],"value":{"type":"typeOrAlias","typeOrAlias":{"name":"Bullet"}}},{"range":[1,61,1,77],"value":{"type":"function","function":{"name":"recCollisionTest"}}},{"range":[1,78,1,87],"value":{"type":"function","function":{"name":"recUpdate"}}},{"range":[1,88,1,92],"value":{"type":"typeOrAlias","typeOrAlias":{"name":"Room"}}},{"range":[1,93,1,101],"value":{"type":"typeOrAlias","typeOrAlias":{"name":"Treasure"}}},{"range":[1,102,1,105],"value":{"type":"typeOrAlias","typeOrAlias":{"name":"Map"}}},{"range":[1,106,1,114],"value":{"type":"typeOrAlias","typeOrAlias":{"name":"Obstacle"}}}]}}}}},"imports":[{"range":[2,1,2,14],"value":{"moduleName":{"range":[2,8,2,14],"value":["Random"]},"moduleAlias":null,"exposingList":null}}],"declarations":[{"range":[11,1,16,6],"value":{"type":"typeAlias","typeAlias":{"documentation":null,"name":{"range":[11,12,11,15],"value":"Rec"},"generics":[],"typeAnnotation":{"range":[12,5,16,6],"value":{"type":"record","record":{"value":[{"range":[12,7,12,17],"value":{"name":{"range":[12,7,12,9],"value":"cx"},"typeAnnotation":{"range":[12,12,12,17],"value":{"type":"typed","typed":{"moduleNameAndName":{"range":[12,12,12,17],"value":{"moduleName":[],"name":"Float"}},"args":[]}}}}},{"range":[13,5,14,5],"value":{"name":{"range":[13,7,13,9],"value":"cy"},"typeAnnotation":{"range":[13,12,13,17],"value":{"type":"typed","typed":{"moduleNameAndName":{"range":[13,12,13,17],"value":{"moduleName":[],"name":"Float"}},"args":[]}}}}},{"range":[14,5,15,5],"value":{"name":{"range":[14,7,14,16],"value":"halfWidth"},"typeAnnotation":{"range":[14,19,14,24],"value":{"type":"typed","typed":{"moduleNameAndName":{"range":[14,19,14,24],"value":{"moduleName":[],"name":"Float"}},"args":[]}}}}},{"range":[15,5,16,5],"value":{"name":{"range":[15,7,15,17],"value":"halfHeight"},"typeAnnotation":{"range":[15,20,15,25],"value":{"type":"typed","typed":{"moduleNameAndName":{"range":[15,20,15,25],"value":{"moduleName":[],"name":"Float"}},"args":[]}}}}}]}}}}}},{"range":[18,1,24,6],"value":{"type":"typeAlias","typeAlias":{"documentation":null,"name":{"range":[18,12,18,21],"value":"Rectangle"},"generics":[],"typeAnnotation":{"range":[19,5,24,6],"value":{"type":"record","record":{"value":[{"range":[19,7,19,16],"value":{"name":{"range":[19,7,19,8],"value":"x"},"typeAnnotation":{"range":[19,11,19,16],"value":{"type":"typed","typed":{"moduleNameAndName":{"range":[19,11,19,16],"value":{"moduleName":[],"name":"Float"}},"args":[]}}}}},{"range":[20,5,21,5],"value":{"name":{"range":[20,7,20,8],"value":"y"},"typeAnnotation":{"range":[20,11,20,16],"value":{"type":"typed","typed":{"moduleNameAndName":{"range":[20,11,20,16],"value":{"moduleName":[],"name":"Float"}},"args":[]}}}}},{"range":[21,5,22,5],"value":{"name":{"range":[21,7,21,12],"value":"width"},"typeAnnotation":{"range":[21,15,21,20],"value":{"type":"typed","typed":{"moduleNameAndName":{"range":[21,15,21,20],"value":{"moduleName":[],"name":"Float"}},"args":[]}}}}},{"range":[22,5,23,5],"value":{"name":{"range":[22,7,22,13],"value":"height"},"typeAnnotation":{"range":[22,16,22,21],"value":{"type":"typed","typed":{"moduleNameAndName":{"range":[22,16,22,21],"value":{"moduleName":[],"name":"Float"}},"args":[]}}}}},{"range":[23,5,24,5],"value":{"name":{"range":[23,7,23,11],"value":"edge"},"typeAnnotation":{"range":[23,14,23,17],"value":{"type":"typed","typed":{"moduleNameAndName":{"range":[23,14,23,17],"value":{"moduleName":[],"name":"Rec"}},"args":[]}}}}}]}}}}}},{"range":[26,1,34,6],"value":{"type":"typeAlias","typeAlias":{"documentation":null,"name":{"range":[26,12,26,18],"value":"Player"},"generics":[],"typeAnnotation":{"range":[27,5,34,6],"value":{"type":"record","record":{"value":[{"range":[27,7,27,16],"value":{"name":{"range":[27,7,27,8],"value":"x"},"typeAnnotation":{"range":[27,11,27,16],"value":{"type":"typed","typed":{"moduleNameAndName":{"range":[27,11,27,16],"value":{"moduleName":[],"name":"Float"}},"args":[]}}}}},{"range":[28,5,29,5],"value":{"name":{"range":[28,7,28,8],"value":"y"},"typeAnnotation":{"range":[28,11,28,16],"value":{"type":"typed","typed":{"moduleNameAndName":{"range":[28,11,28,16],"value":{"moduleName":[],"name":"Float"}},"args":[]}}}}},{"range":[29,5,30,5],"value":{"name":{"range":[29,7,29,8],"value":"r"},"typeAnnotation":{"range":[29,11,29,16],"value":{"type":"typed","typed":{"moduleNameAndName":{"range":[29,11,29,16],"value":{"moduleName":[],"name":"Float"}},"args":[]}}}}},{"range":[30,5,31,5],"value":{"name":{"range":[30,7,30,13],"value":"rotate"},"typeAnnotation":{"range":[30,16,30,21],"value":{"type":"typed","typed":{"moduleNameAndName":{"range":[30,16,30,21],"value":{"moduleName":[],"name":"Float"}},"args":[]}}}}},{"range":[31,5,32,5],"value":{"name":{"range":[31,7,31,11],"value":"name"},"typeAnnotation":{"range":[31,14,31,20],"value":{"type":"typed","typed":{"moduleNameAndName":{"range":[31,14,31,20],"value":{"moduleName":[],"name":"String"}},"args":[]}}}}},{"range":[32,5,33,5],"value":{"name":{"range":[32,7,32,12],"value":"score"},"typeAnnotation":{"range":[32,15,32,20],"value":{"type":"typed","typed":{"moduleNameAndName":{"range":[32,15,32,20],"value":{"moduleName":[],"name":"Float"}},"args":[]}}}}},{"range":[33,5,34,5],"value":{"name":{"range":[33,7,33,10],"value":"die"},"typeAnnotation":{"range":[33,13,33,17],"value":{"type":"typed","typed":{"moduleNameAndName":{"range":[33,13,33,17],"value":{"moduleName":[],"name":"Bool"}},"args":[]}}}}}]}}}}}},{"range":[36,1,43,6],"value":{"type":"typeAlias","typeAlias":{"documentation":null,"name":{"range":[36,12,36,18],"value":"Bullet"},"generics":[],"typeAnnotation":{"range":[37,5,43,6],"value":{"type":"record","record":{"value":[{"range":[37,7,37,16],"value":{"name":{"range":[37,7,37,8],"value":"x"},"typeAnnotation":{"range":[37,11,37,16],"value":{"type":"typed","typed":{"moduleNameAndName":{"range":[37,11,37,16],"value":{"moduleName":[],"name":"Float"}},"args":[]}}}}},{"range":[38,5,39,5],"value":{"name":{"range":[38,7,38,8],"value":"y"},"typeAnnotation":{"range":[38,11,38,16],"value":{"type":"typed","typed":{"moduleNameAndName":{"range":[38,11,38,16],"value":{"moduleName":[],"name":"Float"}},"args":[]}}}}},{"range":[39,5,40,5],"value":{"name":{"range":[39,7,39,8],"value":"r"},"typeAnnotation":{"range":[39,11,39,16],"value":{"type":"typed","typed":{"moduleNameAndName":{"range":[39,11,39,16],"value":{"moduleName":[],"name":"Float"}},"args":[]}}}}},{"range":[40,5,41,5],"value":{"name":{"range":[40,7,40,13],"value":"speedX"},"typeAnnotation":{"range":[40,16,40,21],"value":{"type":"typed","typed":{"moduleNameAndName":{"range":[40,16,40,21],"value":{"moduleName":[],"name":"Float"}},"args":[]}}}}},{"range":[41,5,42,5],"value":{"name":{"range":[41,7,41,13],"value":"speedY"},"typeAnnotation":{"range":[41,16,41,21],"value":{"type":"typed","typed":{"moduleNameAndName":{"range":[41,16,41,21],"value":{"moduleName":[],"name":"Float"}},"args":[]}}}}},{"range":[42,5,43,5],"value":{"name":{"range":[42,7,42,16],"value":"collision"},"typeAnnotation":{"range":[42,19,42,23],"value":{"type":"typed","typed":{"moduleNameAndName":{"range":[42,19,42,23],"value":{"moduleName":[],"name":"Bool"}},"args":[]}}}}}]}}}}}},{"range":[45,1,46,7],"value":{"type":"typeAlias","typeAlias":{"documentation":null,"name":{"range":[45,12,45,19],"value":"Monster"},"generics":[],"typeAnnotation":{"range":[46,5,46,7],"value":{"type":"record","record":{"value":[]}}}}}},{"range":[48,1,50,6],"value":{"type":"typeAlias","typeAlias":{"documentation":null,"name":{"range":[48,12,48,20],"value":"Treasure"},"generics":[],"typeAnnotation":{"range":[49,5,50,6],"value":{"type":"record","record":{"value":[{"range":[49,7,49,27],"value":{"name":{"range":[49,7,49,15],"value":"position"},"typeAnnotation":{"range":[49,18,49,27],"value":{"type":"tupled","tupled":{"values":[{"range":[49,19,49,22],"value":{"type":"typed","typed":{"moduleNameAndName":{"range":[49,19,49,22],"value":{"moduleName":[],"name":"Int"}},"args":[]}}},{"range":[49,23,49,26],"value":{"type":"typed","typed":{"moduleNameAndName":{"range":[49,23,49,26],"value":{"moduleName":[],"name":"Int"}},"args":[]}}}]}}}}}]}}}}}},{"range":[52,1,55,6],"value":{"type":"typeAlias","typeAlias":{"documentation":null,"name":{"range":[52,12,52,20],"value":"Obstacle"},"generics":[],"typeAnnotation":{"range":[53,5,55,6],"value":{"type":"record","record":{"value":[{"range":[53,7,53,27],"value":{"name":{"range":[53,7,53,15],"value":"position"},"typeAnnotation":{"range":[53,18,53,27],"value":{"type":"typed","typed":{"moduleNameAndName":{"range":[53,18,53,27],"value":{"moduleName":[],"name":"Rectangle"}},"args":[]}}}}}]}}}}}},{"range":[58,1,67,6],"value":{"type":"typeAlias","typeAlias":{"documentation":null,"name":{"range":[58,12,58,16],"value":"Room"},"generics":[],"typeAnnotation":{"range":[59,5,67,6],"value":{"type":"record","record":{"value":[{"range":[59,7,59,27],"value":{"name":{"range":[59,7,59,15],"value":"position"},"typeAnnotation":{"range":[59,18,59,27],"value":{"type":"tupled","tupled":{"values":[{"range":[59,19,59,22],"value":{"type":"typed","typed":{"moduleNameAndName":{"range":[59,19,59,22],"value":{"moduleName":[],"name":"Int"}},"args":[]}}},{"range":[59,23,59,26],"value":{"type":"typed","typed":{"moduleNameAndName":{"range":[59,23,59,26],"value":{"moduleName":[],"name":"Int"}},"args":[]}}}]}}}}},{"range":[60,5,61,5],"value":{"name":{"range":[60,7,60,11],"value":"gate"},"typeAnnotation":{"range":[60,14,60,18],"value":{"type":"typed","typed":{"moduleNameAndName":{"range":[60,14,60,18],"value":{"moduleName":[],"name":"Bool"}},"args":[]}}}}},{"range":[61,5,62,5],"value":{"name":{"range":[61,7,61,11],"value":"boss"},"typeAnnotation":{"range":[61,14,61,18],"value":{"type":"typed","typed":{"moduleNameAndName":{"range":[61,14,61,18],"value":{"moduleName":[],"name":"Bool"}},"args":[]}}}}},{"range":[62,5,63,5],"value":{"name":{"range":[62,7,62,16],"value":"obstacles"},"typeAnnotation":{"range":[62,19,62,32],"value":{"type":"typed","typed":{"moduleNameAndName":{"range":[62,19,62,23],"value":{"moduleName":[],"name":"List"}},"args":[{"range":[62,24,62,32],"value":{"type":"typed","typed":{"moduleNameAndName":{"range":[62,24,62,32],"value":{"moduleName":[],"name":"Obstacle"}},"args":[]}}}]}}}}},{"range":[63,5,64,5],"value":{"name":{"range":[63,7,63,15],"value":"monsters"},"typeAnnotation":{"range":[63,18,63,30],"value":{"type":"typed","typed":{"moduleNameAndName":{"range":[63,18,63,22],"value":{"moduleName":[],"name":"List"}},"args":[{"range":[63,23,63,30],"value":{"type":"typed","typed":{"moduleNameAndName":{"range":[63,23,63,30],"value":{"moduleName":[],"name":"Monster"}},"args":[]}}}]}}}}},{"range":[64,5,65,5],"value":{"name":{"range":[64,7,64,15],"value":"treasure"},"typeAnnotation":{"range":[64,18,64,26],"value":{"type":"typed","typed":{"moduleNameAndName":{"range":[64,18,64,26],"value":{"moduleName":[],"name":"Treasure"}},"args":[]}}}}},{"range":[65,5,66,5],"value":{"name":{"range":[65,7,65,11],"value":"road"},"typeAnnotation":{"range":[65,14,65,28],"value":{"type":"typed","typed":{"moduleNameAndName":{"range":[65,14,65,18],"value":{"moduleName":[],"name":"List"}},"args":[{"range":[65,19,65,28],"value":{"type":"tupled","tupled":{"values":[{"range":[65,20,65,23],"value":{"type":"typed","typed":{"moduleNameAndName":{"range":[65,20,65,23],"value":{"moduleName":[],"name":"Int"}},"args":[]}}},{"range":[65,24,65,27],"value":{"type":"typed","typed":{"moduleNameAndName":{"range":[65,24,65,27],"value":{"moduleName":[],"name":"Int"}},"args":[]}}}]}}}]}}}}},{"range":[66,5,67,5],"value":{"name":{"range":[66,7,66,11],"value":"rank"},"typeAnnotation":{"range":[66,14,66,17],"value":{"type":"typed","typed":{"moduleNameAndName":{"range":[66,14,66,17],"value":{"moduleName":[],"name":"Int"}},"args":[]}}}}}]}}}}}},{"range":[69,1,75,6],"value":{"type":"typeAlias","typeAlias":{"documentation":null,"name":{"range":[69,12,69,15],"value":"Map"},"generics":[],"typeAnnotation":{"range":[70,5,75,6],"value":{"type":"record","record":{"value":[{"range":[70,7,70,29],"value":{"name":{"range":[70,7,70,12],"value":"walls"},"typeAnnotation":{"range":[70,15,70,29],"value":{"type":"typed","typed":{"moduleNameAndName":{"range":[70,15,70,19],"value":{"moduleName":[],"name":"List"}},"args":[{"range":[70,20,70,29],"value":{"type":"typed","typed":{"moduleNameAndName":{"range":[70,20,70,29],"value":{"moduleName":[],"name":"Rectangle"}},"args":[]}}}]}}}}},{"range":[71,5,72,5],"value":{"name":{"range":[71,7,71,12],"value":"roads"},"typeAnnotation":{"range":[71,15,71,29],"value":{"type":"typed","typed":{"moduleNameAndName":{"range":[71,15,71,19],"value":{"moduleName":[],"name":"List"}},"args":[{"range":[71,20,71,29],"value":{"type":"typed","typed":{"moduleNameAndName":{"range":[71,20,71,29],"value":{"moduleName":[],"name":"Rectangle"}},"args":[]}}}]}}}}},{"range":[72,5,73,5],"value":{"name":{"range":[72,7,72,16],"value":"obstacles"},"typeAnnotation":{"range":[72,19,72,33],"value":{"type":"typed","typed":{"moduleNameAndName":{"range":[72,19,72,23],"value":{"moduleName":[],"name":"List"}},"args":[{"range":[72,24,72,33],"value":{"type":"typed","typed":{"moduleNameAndName":{"range":[72,24,72,33],"value":{"moduleName":[],"name":"Rectangle"}},"args":[]}}}]}}}}},{"range":[73,5,74,5],"value":{"name":{"range":[73,7,73,15],"value":"monsters"},"typeAnnotation":{"range":[73,18,73,32],"value":{"type":"typed","typed":{"moduleNameAndName":{"range":[73,18,73,22],"value":{"moduleName":[],"name":"List"}},"args":[{"range":[73,23,73,32],"value":{"type":"typed","typed":{"moduleNameAndName":{"range":[73,23,73,32],"value":{"moduleName":[],"name":"Rectangle"}},"args":[]}}}]}}}}},{"range":[74,5,75,5],"value":{"name":{"range":[74,7,74,12],"value":"doors"},"typeAnnotation":{"range":[74,15,74,29],"value":{"type":"typed","typed":{"moduleNameAndName":{"range":[74,15,74,19],"value":{"moduleName":[],"name":"List"}},"args":[{"range":[74,20,74,29],"value":{"type":"typed","typed":{"moduleNameAndName":{"range":[74,20,74,29],"value":{"moduleName":[],"name":"Rectangle"}},"args":[]}}}]}}}}}]}}}}}},{"range":[78,1,94,6],"value":{"type":"typeAlias","typeAlias":{"documentation":null,"name":{"range":[78,12,78,14],"value":"Me"},"generics":[],"typeAnnotation":{"range":[79,5,94,6],"value":{"type":"record","record":{"value":[{"range":[79,7,79,16],"value":{"name":{"range":[79,7,79,8],"value":"x"},"typeAnnotation":{"range":[79,11,79,16],"value":{"type":"typed","typed":{"moduleNameAndName":{"range":[79,11,79,16],"value":{"moduleName":[],"name":"Float"}},"args":[]}}}}},{"range":[80,7,81,7],"value":{"name":{"range":[80,9,80,10],"value":"y"},"typeAnnotation":{"range":[80,13,80,18],"value":{"type":"typed","typed":{"moduleNameAndName":{"range":[80,13,80,18],"value":{"moduleName":[],"name":"Float"}},"args":[]}}}}},{"range":[81,7,82,7],"value":{"name":{"range":[81,9,81,10],"value":"r"},"typeAnnotation":{"range":[81,13,81,18],"value":{"type":"typed","typed":{"moduleNameAndName":{"range":[81,13,81,18],"value":{"moduleName":[],"name":"Float"}},"args":[]}}}}},{"range":[82,7,83,7],"value":{"name":{"range":[82,9,82,15],"value":"xSpeed"},"typeAnnotation":{"range":[82,18,82,23],"value":{"type":"typed","typed":{"moduleNameAndName":{"range":[82,18,82,23],"value":{"moduleName":[],"name":"Float"}},"args":[]}}}}},{"range":[83,7,84,7],"value":{"name":{"range":[83,9,83,15],"value":"ySpeed"},"typeAnnotation":{"range":[83,18,83,23],"value":{"type":"typed","typed":{"moduleNameAndName":{"range":[83,18,83,23],"value":{"moduleName":[],"name":"Float"}},"args":[]}}}}},{"range":[84,7,85,7],"value":{"name":{"range":[84,9,84,15],"value":"rotate"},"typeAnnotation":{"range":[84,18,84,23],"value":{"type":"typed","typed":{"moduleNameAndName":{"range":[84,18,84,23],"value":{"moduleName":[],"name":"Float"}},"args":[]}}}}},{"range":[85,7,86,7],"value":{"name":{"range":[85,9,85,15],"value":"moveUp"},"typeAnnotation":{"range":[85,18,85,22],"value":{"type":"typed","typed":{"moduleNameAndName":{"range":[85,18,85,22],"value":{"moduleName":[],"name":"Bool"}},"args":[]}}}}},{"range":[86,7,87,7],"value":{"name":{"range":[86,9,86,18],"value":"moveRight"},"typeAnnotation":{"range":[86,21,86,25],"value":{"type":"typed","typed":{"moduleNameAndName":{"range":[86,21,86,25],"value":{"moduleName":[],"name":"Bool"}},"args":[]}}}}},{"range":[87,7,88,7],"value":{"name":{"range":[87,9,87,17],"value":"moveLeft"},"typeAnnotation":{"range":[87,20,87,24],"value":{"type":"typed","typed":{"moduleNameAndName":{"range":[87,20,87,24],"value":{"moduleName":[],"name":"Bool"}},"args":[]}}}}},{"range":[88,7,89,7],"value":{"name":{"range":[88,9,88,17],"value":"moveDown"},"typeAnnotation":{"range":[88,20,88,24],"value":{"type":"typed","typed":{"moduleNameAndName":{"range":[88,20,88,24],"value":{"moduleName":[],"name":"Bool"}},"args":[]}}}}},{"range":[89,7,90,7],"value":{"name":{"range":[89,9,89,13],"value":"edge"},"typeAnnotation":{"range":[89,16,89,19],"value":{"type":"typed","typed":{"moduleNameAndName":{"range":[89,16,89,19],"value":{"moduleName":[],"name":"Rec"}},"args":[]}}}}},{"range":[90,7,91,7],"value":{"name":{"range":[90,9,90,18],"value":"mouseData"},"typeAnnotation":{"range":[90,21,90,34],"value":{"type":"tupled","tupled":{"values":[{"range":[90,22,90,27],"value":{"type":"typed","typed":{"moduleNameAndName":{"range":[90,22,90,27],"value":{"moduleName":[],"name":"Float"}},"args":[]}}},{"range":[90,28,90,33],"value":{"type":"typed","typed":{"moduleNameAndName":{"range":[90,28,90,33],"value":{"moduleName":[],"name":"Float"}},"args":[]}}}]}}}}},{"range":[91,7,92,7],"value":{"name":{"range":[91,9,91,13],"value":"fire"},"typeAnnotation":{"range":[91,16,91,20],"value":{"type":"typed","typed":{"moduleNameAndName":{"range":[91,16,91,20],"value":{"moduleName":[],"name":"Bool"}},"args":[]}}}}},{"range":[92,7,93,7],"value":{"name":{"range":[92,9,92,13],"value":"name"},"typeAnnotation":{"range":[92,16,92,22],"value":{"type":"typed","typed":{"moduleNameAndName":{"range":[92,16,92,22],"value":{"moduleName":[],"name":"String"}},"args":[]}}}}},{"range":[93,7,94,5],"value":{"name":{"range":[93,9,93,14],"value":"score"},"typeAnnotation":{"range":[93,17,93,22],"value":{"type":"typed","typed":{"moduleNameAndName":{"range":[93,17,93,22],"value":{"moduleName":[],"name":"Float"}},"args":[]}}}}}]}}}}}},{"range":[96,1,104,6],"value":{"type":"typeAlias","typeAlias":{"documentation":null,"name":{"range":[96,12,96,17],"value":"Model"},"generics":[],"typeAnnotation":{"range":[97,5,104,6],"value":{"type":"record","record":{"value":[{"range":[98,7,98,19],"value":{"name":{"range":[98,7,98,13],"value":"myself"},"typeAnnotation":{"range":[98,17,98,19],"value":{"type":"typed","typed":{"moduleNameAndName":{"range":[98,17,98,19],"value":{"moduleName":[],"name":"Me"}},"args":[]}}}}},{"range":[99,5,100,5],"value":{"name":{"range":[99,7,99,13],"value":"bullet"},"typeAnnotation":{"range":[99,16,99,27],"value":{"type":"typed","typed":{"moduleNameAndName":{"range":[99,16,99,20],"value":{"moduleName":[],"name":"List"}},"args":[{"range":[99,21,99,27],"value":{"type":"typed","typed":{"moduleNameAndName":{"range":[99,21,99,27],"value":{"moduleName":[],"name":"Bullet"}},"args":[]}}}]}}}}},{"range":[100,5,101,5],"value":{"name":{"range":[100,7,100,20],"value":"bulletViewbox"},"typeAnnotation":{"range":[100,23,100,34],"value":{"type":"typed","typed":{"moduleNameAndName":{"range":[100,23,100,27],"value":{"moduleName":[],"name":"List"}},"args":[{"range":[100,28,100,34],"value":{"type":"typed","typed":{"moduleNameAndName":{"range":[100,28,100,34],"value":{"moduleName":[],"name":"Bullet"}},"args":[]}}}]}}}}},{"range":[101,5,102,5],"value":{"name":{"range":[101,7,101,10],"value":"map"},"typeAnnotation":{"range":[101,13,101,16],"value":{"type":"typed","typed":{"moduleNameAndName":{"range":[101,13,101,16],"value":{"moduleName":[],"name":"Map"}},"args":[]}}}}},{"range":[102,5,103,5],"value":{"name":{"range":[102,7,102,12],"value":"rooms"},"typeAnnotation":{"range":[102,15,102,38],"value":{"type":"tupled","tupled":{"values":[{"range":[102,16,102,25],"value":{"type":"typed","typed":{"moduleNameAndName":{"range":[102,16,102,20],"value":{"moduleName":[],"name":"List"}},"args":[{"range":[102,21,102,25],"value":{"type":"typed","typed":{"moduleNameAndName":{"range":[102,21,102,25],"value":{"moduleName":[],"name":"Room"}},"args":[]}}}]}}},{"range":[102,26,102,37],"value":{"type":"typed","typed":{"moduleNameAndName":{"range":[102,26,102,37],"value":{"moduleName":["Random"],"name":"Seed"}},"args":[]}}}]}}}}},{"range":[103,5,104,5],"value":{"name":{"range":[103,7,103,14],"value":"viewbox"},"typeAnnotation":{"range":[103,17,103,20],"value":{"type":"typed","typed":{"moduleNameAndName":{"range":[103,17,103,20],"value":{"moduleName":[],"name":"Map"}},"args":[]}}}}}]}}}}}},{"range":[107,1,109,127],"value":{"type":"function","function":{"documentation":null,"signature":{"range":[107,1,107,38],"value":{"name":{"range":[107,1,107,17],"value":"recCollisionTest"},"typeAnnotation":{"range":[107,20,107,38],"value":{"type":"function","function":{"left":{"range":[107,20,107,23],"value":{"type":"typed","typed":{"moduleNameAndName":{"range":[107,20,107,23],"value":{"moduleName":[],"name":"Rec"}},"args":[]}}},"right":{"range":[107,27,107,38],"value":{"type":"function","function":{"left":{"range":[107,27,107,30],"value":{"type":"typed","typed":{"moduleNameAndName":{"range":[107,27,107,30],"value":{"moduleName":[],"name":"Rec"}},"args":[]}}},"right":{"range":[107,34,107,38],"value":{"type":"typed","typed":{"moduleNameAndName":{"range":[107,34,107,38],"value":{"moduleName":[],"name":"Bool"}},"args":[]}}}}}}}}}}},"declaration":{"range":[108,1,109,127],"value":{"name":{"range":[108,1,108,17],"value":"recCollisionTest"},"arguments":[{"range":[108,18,108,22],"value":{"type":"var","var":{"value":"rec1"}}},{"range":[108,23,108,27],"value":{"type":"var","var":{"value":"rec2"}}}],"expression":{"range":[109,5,109,127],"value":{"type":"application","application":[{"range":[109,5,109,63],"value":{"type":"parenthesized","parenthesized":{"range":[109,6,109,62],"value":{"type":"application","application":[{"range":[109,6,109,9],"value":{"type":"functionOrValue","functionOrValue":{"moduleName":[],"name":"abs"}}},{"range":[109,9,109,28],"value":{"type":"parenthesized","parenthesized":{"range":[109,14,109,27],"value":{"type":"application","application":[{"range":[109,14,109,17],"value":{"type":"recordAccess","recordAccess":{"expression":{"range":[109,10,109,14],"value":{"type":"functionOrValue","functionOrValue":{"moduleName":[],"name":"rec1"}}},"name":{"range":[109,15,109,17],"value":"cx"}}}},{"range":[109,18,109,20],"value":{"type":"operator","operator":"-"}},{"range":[109,24,109,27],"value":{"type":"recordAccess","recordAccess":{"expression":{"range":[109,20,109,24],"value":{"type":"functionOrValue","functionOrValue":{"moduleName":[],"name":"rec2"}}},"name":{"range":[109,25,109,27],"value":"cx"}}}}]}}}},{"range":[109,29,109,30],"value":{"type":"operator","operator":"<"}},{"range":[109,35,109,45],"value":{"type":"recordAccess","recordAccess":{"expression":{"range":[109,31,109,35],"value":{"type":"functionOrValue","functionOrValue":{"moduleName":[],"name":"rec1"}}},"name":{"range":[109,36,109,45],"value":"halfWidth"}}}},{"range":[109,46,109,47],"value":{"type":"operator","operator":"+"}},{"range":[109,52,109,62],"value":{"type":"recordAccess","recordAccess":{"expression":{"range":[109,48,109,52],"value":{"type":"functionOrValue","functionOrValue":{"moduleName":[],"name":"rec2"}}},"name":{"range":[109,53,109,62],"value":"halfWidth"}}}}]}}}},{"range":[109,64,109,66],"value":{"type":"operator","operator":"&&"}},{"range":[109,67,109,127],"value":{"type":"parenthesized","parenthesized":{"range":[109,68,109,126],"value":{"type":"application","application":[{"range":[109,68,109,71],"value":{"type":"functionOrValue","functionOrValue":{"moduleName":[],"name":"abs"}}},{"range":[109,71,109,90],"value":{"type":"parenthesized","parenthesized":{"range":[109,76,109,89],"value":{"type":"application","application":[{"range":[109,76,109,79],"value":{"type":"recordAccess","recordAccess":{"expression":{"range":[109,72,109,76],"value":{"type":"functionOrValue","functionOrValue":{"moduleName":[],"name":"rec1"}}},"name":{"range":[109,77,109,79],"value":"cy"}}}},{"range":[109,80,109,82],"value":{"type":"operator","operator":"-"}},{"range":[109,86,109,89],"value":{"type":"recordAccess","recordAccess":{"expression":{"range":[109,82,109,86],"value":{"type":"functionOrValue","functionOrValue":{"moduleName":[],"name":"rec2"}}},"name":{"range":[109,87,109,89],"value":"cy"}}}}]}}}},{"range":[109,91,109,92],"value":{"type":"operator","operator":"<"}},{"range":[109,97,109,108],"value":{"type":"recordAccess","recordAccess":{"expression":{"range":[109,93,109,97],"value":{"type":"functionOrValue","functionOrValue":{"moduleName":[],"name":"rec1"}}},"name":{"range":[109,98,109,108],"value":"halfHeight"}}}},{"range":[109,109,109,110],"value":{"type":"operator","operator":"+"}},{"range":[109,115,109,126],"value":{"type":"recordAccess","recordAccess":{"expression":{"range":[109,111,109,115],"value":{"type":"functionOrValue","functionOrValue":{"moduleName":[],"name":"rec2"}}},"name":{"range":[109,116,109,126],"value":"halfHeight"}}}}]}}}}]}}}}}}},{"range":[111,1,121,1],"value":{"type":"function","function":{"documentation":null,"signature":{"range":[111,1,111,35],"value":{"name":{"range":[111,1,111,10],"value":"recUpdate"},"typeAnnotation":{"range":[111,13,111,35],"value":{"type":"function","function":{"left":{"range":[111,13,111,22],"value":{"type":"typed","typed":{"moduleNameAndName":{"range":[111,13,111,22],"value":{"moduleName":[],"name":"Rectangle"}},"args":[]}}},"right":{"range":[111,26,111,35],"value":{"type":"typed","typed":{"moduleNameAndName":{"range":[111,26,111,35],"value":{"moduleName":[],"name":"Rectangle"}},"args":[]}}}}}}}},"declaration":{"range":[112,1,121,1],"value":{"name":{"range":[112,1,112,10],"value":"recUpdate"},"arguments":[{"range":[112,11,112,16],"value":{"type":"var","var":{"value":"model"}}}],"expression":{"range":[113,5,121,1],"value":{"type":"let","let":{"declarations":[{"range":[114,9,115,9],"value":{"type":"function","function":{"documentation":null,"signature":null,"declaration":{"range":[114,9,114,32],"value":{"name":{"range":[114,9,114,14],"value":"halfx"},"arguments":[],"expression":{"range":[114,22,114,32],"value":{"type":"application","application":[{"range":[114,22,114,28],"value":{"type":"recordAccess","recordAccess":{"expression":{"range":[114,17,114,22],"value":{"type":"functionOrValue","functionOrValue":{"moduleName":[],"name":"model"}}},"name":{"range":[114,23,114,28],"value":"width"}}}},{"range":[114,29,114,30],"value":{"type":"operator","operator":"/"}},{"range":[114,31,114,32],"value":{"type":"integer","integer":2}}]}}}}}}},{"range":[115,9,116,9],"value":{"type":"function","function":{"documentation":null,"signature":null,"declaration":{"range":[115,9,115,32],"value":{"name":{"range":[115,9,115,14],"value":"halfy"},"arguments":[],"expression":{"range":[115,22,115,32],"value":{"type":"application","application":[{"range":[115,22,115,29],"value":{"type":"recordAccess","recordAccess":{"expression":{"range":[115,17,115,22],"value":{"type":"functionOrValue","functionOrValue":{"moduleName":[],"name":"model"}}},"name":{"range":[115,23,115,29],"value":"height"}}}},{"range":[115,30,115,31],"value":{"type":"operator","operator":"/"}},{"range":[115,31,115,32],"value":{"type":"integer","integer":2}}]}}}}}}},{"range":[116,9,117,9],"value":{"type":"function","function":{"documentation":null,"signature":null,"declaration":{"range":[116,9,116,31],"value":{"name":{"range":[116,9,116,13],"value":"newx"},"arguments":[],"expression":{"range":[116,21,116,31],"value":{"type":"application","application":[{"range":[116,21,116,23],"value":{"type":"recordAccess","recordAccess":{"expression":{"range":[116,16,116,21],"value":{"type":"functionOrValue","functionOrValue":{"moduleName":[],"name":"model"}}},"name":{"range":[116,22,116,23],"value":"x"}}}},{"range":[116,24,116,25],"value":{"type":"operator","operator":"+"}},{"range":[116,26,116,31],"value":{"type":"functionOrValue","functionOrValue":{"moduleName":[],"name":"halfx"}}}]}}}}}}},{"range":[117,9,118,9],"value":{"type":"function","function":{"documentation":null,"signature":null,"declaration":{"range":[117,9,117,31],"value":{"name":{"range":[117,9,117,13],"value":"newy"},"arguments":[],"expression":{"range":[117,21,117,31],"value":{"type":"application","application":[{"range":[117,21,117,23],"value":{"type":"recordAccess","recordAccess":{"expression":{"range":[117,16,117,21],"value":{"type":"functionOrValue","functionOrValue":{"moduleName":[],"name":"model"}}},"name":{"range":[117,22,117,23],"value":"y"}}}},{"range":[117,24,117,25],"value":{"type":"operator","operator":"+"}},{"range":[117,26,117,31],"value":{"type":"functionOrValue","functionOrValue":{"moduleName":[],"name":"halfy"}}}]}}}}}}},{"range":[118,9,119,5],"value":{"type":"function","function":{"documentation":null,"signature":null,"declaration":{"range":[118,9,118,43],"value":{"name":{"range":[118,9,118,15],"value":"newRec"},"arguments":[],"expression":{"range":[118,18,118,43],"value":{"type":"application","application":[{"range":[118,18,118,21],"value":{"type":"functionOrValue","functionOrValue":{"moduleName":[],"name":"Rec"}}},{"range":[118,22,118,26],"value":{"type":"functionOrValue","functionOrValue":{"moduleName":[],"name":"newx"}}},{"range":[118,27,118,31],"value":{"type":"functionOrValue","functionOrValue":{"moduleName":[],"name":"newy"}}},{"range":[118,32,118,37],"value":{"type":"functionOrValue","functionOrValue":{"moduleName":[],"name":"halfx"}}},{"range":[118,38,118,43],"value":{"type":"functionOrValue","functionOrValue":{"moduleName":[],"name":"halfy"}}}]}}}}}}}],"expression":{"range":[120,9,120,32],"value":{"type":"recordUpdate","recordUpdate":{"name":{"range":[120,11,120,16],"value":"model"},"updates":[{"range":[120,18,120,31],"value":{"field":{"range":[120,18,120,22],"value":"edge"},"expression":{"range":[120,25,120,31],"value":{"type":"functionOrValue","functionOrValue":{"moduleName":[],"name":"newRec"}}}}}]}}}}}}}}}}}],"comments":[{"range":[91,21,91,36],"value":"-- 到时候用sum type"},{"range":[66,18,66,35],"value":"-- rank 越低，怪难度越高？"},{"range":[65,29,65,35],"value":"-- 邻接表"},{"range":[54,5,54,20],"value":"-- , type : Int"},{"range":[9,1,9,9],"value":"--     }"},{"range":[8,1,8,29],"value":"--     , offsetWidth : Float"},{"range":[7,1,7,30],"value":"--     , offsetHeight : Float"},{"range":[6,1,6,23],"value":"--     , offsetY : Int"},{"range":[5,1,5,23],"value":"--     { offsetX : Int"},{"range":[4,1,4,30],"value":"-- type alias MouseMoveData ="}]}